{"cameraMode":{"drawMode":0,"name":"Shaded","section":"Shading Mode"},"sceneLighting":true,"audioPlay":false,"sceneViewState":{"showFog":true,"showMaterialUpdate":false,"showSkybox":true,"showFlares":true,"showImageEffects":true,"showParticleSystems":true},"in2DMode":false,"pivot":{"x":201.2471466064453,"y":51.70945739746094,"z":-16.5572509765625},"rotation":{"x":0.21635733544826508,"y":0.153459832072258,"z":-0.03426063433289528,"w":0.9637183547019959},"size":416.9533996582031,"orthographic":false}