{"cameraMode":{"drawMode":0,"name":"Shaded","section":"Shading Mode"},"sceneLighting":true,"audioPlay":false,"sceneViewState":{"showFog":true,"showMaterialUpdate":false,"showSkybox":true,"showFlares":true,"showImageEffects":true,"showParticleSystems":true},"in2DMode":false,"pivot":{"x":-36.7394905090332,"y":-8.516178131103516,"z":-0.8636112213134766},"rotation":{"x":0.25147610902786257,"y":0.205655038356781,"z":-0.055515121668577197,"w":0.9442269802093506},"size":30.261117935180665,"orthographic":false}