{"cameraMode":{"drawMode":0,"name":"Shaded","section":"Shading Mode"},"sceneLighting":true,"audioPlay":false,"sceneViewState":{"showFog":true,"showMaterialUpdate":false,"showSkybox":true,"showFlares":true,"showImageEffects":true,"showParticleSystems":true},"in2DMode":false,"pivot":{"x":35.24810028076172,"y":-0.5181159973144531,"z":-4.4842376708984379},"rotation":{"x":0.2673405110836029,"y":0.14672619104385377,"z":-0.041298072785139087,"w":0.9515718221664429},"size":59.8131103515625,"orthographic":false}